CHANGELOG
LICENSE
MANIFEST.in
ROADMAP
html_requirements.txt
requirements.txt
setup.cfg
setup.py
test_requirements.txt
piknik/__init__.py
piknik/basket.py
piknik/crypto.py
piknik/error.py
piknik/identity.py
piknik/issue.py
piknik/msg.py
piknik/wrap.py
piknik.egg-info/PKG-INFO
piknik.egg-info/SOURCES.txt
piknik.egg-info/dependency_links.txt
piknik.egg-info/entry_points.txt
piknik.egg-info/requires.txt
piknik.egg-info/top_level.txt
piknik/cli/__init__.py
piknik/cli/add.py
piknik/cli/comment.py
piknik/cli/mod.py
piknik/cli/session.py
piknik/cli/show.py
piknik/render/base.py
piknik/render/html.py
piknik/render/plain.py
piknik/runnable/cmd.py
piknik/store/__init__.py
tests/test_assign.py
tests/test_basic.py
tests/test_crypto.py
tests/test_dep.py
tests/test_html.py
tests/test_issue.py
tests/test_msg.py
tests/test_render.py
tests/test_store.py
tests/test_tag.py