Metadata-Version: 2.1
Name: piknik
Version: 0.3.6
Summary: CLI issue tracker
Home-page: https://git.defalsify.org/piknik
Author: Louis Holbrook
Author-email: dev@holbrook.no
License: GPLv3+
Keywords: bugs,issues,tracker,productivity,git,pgp
Classifier: Programming Language :: Python :: 3
Classifier: Operating System :: OS Independent
Classifier: Development Status :: 3 - Alpha
Classifier: Topic :: Software Development :: Libraries
Classifier: Environment :: Console
Classifier: Intended Audience :: Developers
Classifier: License :: OSI Approved :: GNU General Public License v3 or later (GPLv3+)
Requires-Python: >=3.7
License-File: LICENSE
